[{"_fName":"Varun","_lName":"Brahmane","_address":"Loni","_city":"Ahmadnagar","_state":"Maharashtra","_zip":413713,"_phone":7040391139,"_email":"varun@gmail.com"},{"_fName":"Nikhil","_lName":"Bhot","_address":"Sangamner","_city":"Akole","_state":"Maharashtra","_zip":414565,"_phone":9856783456,"_email":"nikhil@gmail.com"},{"_fName":"Ravi","_lName":"Jadhav","_address":"Karmala","_city":"Solapur","_state":"Maharashtra","_zip":411234,"_phone":9897867554,"_email":"ravi@gmail.com"},{"_fName":"Akshay","_lName":"Chandgude","_address":"Chasnali","_city":"Kopargaon","_state":"Maharashtra","_zip":414141,"_phone":8796568243,"_email":"akshay@gmail.com"},{"_fName":"Vaeun","_lName":"Brahmane","_address":"Rashinar","_city":"belpur","_state":"shrirampur","_zip":413715,"_phone":9595345692,"_email":"sagar@gmail.com"},{"_fName":"Gaurav","_lName":"Brahmane","_address":"loni","_city":"belpur","_state":"maharastra","_zip":413712,"_phone":8600083281,"_email":"gairav@gmil.com"}]